min1129/LinkedList.py
min1129/ListNode.py
min1129/__init__.py
min1129/untitled.py
min1129-0.0.0.3.dist-info/METADATA
min1129-0.0.0.3.dist-info/WHEEL
min1129-0.0.0.3.dist-info/top_level.txt
min1129-0.0.0.3.dist-info/RECORD
