Metadata-Version: 2.1
Name: min1129
Version: 0.0.0.3
Summary: 링크드 리스트의 기본 모듈 구현
Home-page: https://github.com/maminseo/minseo
Author: maminseo
Author-email: mamin1129@naver.com
License: MIT
Requires-Python: >=3.4
Requires-Dist: boto3
Requires-Dist: pymongo
